LICENSE
setup.py
uhf/__init__.py
uhfReaderApi_Cykeo.egg-info/PKG-INFO
uhfReaderApi_Cykeo.egg-info/SOURCES.txt
uhfReaderApi_Cykeo.egg-info/dependency_links.txt
uhfReaderApi_Cykeo.egg-info/requires.txt
uhfReaderApi_Cykeo.egg-info/top_level.txt
uhf/reader/__init__.py
uhf/reader/communication/__init__.py
uhf/reader/communication/gclient.py
uhf/reader/communication/gserver.py
uhf/reader/communication/hid.py
uhf/reader/communication/interface.py
uhf/reader/communication/serial_client.py
uhf/reader/communication/tcp_client.py
uhf/reader/communication/tcp_server.py
uhf/reader/communication/usb_hid.py
uhf/reader/protocol/__init__.py
uhf/reader/protocol/action_param_fail.py
uhf/reader/protocol/action_param_success.py
uhf/reader/protocol/app_all_gpiState.py
uhf/reader/protocol/app_clearCacheData.py
uhf/reader/protocol/app_del_whiteList.py
uhf/reader/protocol/app_get_baseVersion.py
uhf/reader/protocol/app_get_breakpointResume.py
uhf/reader/protocol/app_get_cacheTagData.py
uhf/reader/protocol/app_get_easAlarm.py
uhf/reader/protocol/app_get_ethernetIp.py
uhf/reader/protocol/app_get_gpiState.py
uhf/reader/protocol/app_get_gpiTrigger.py
uhf/reader/protocol/app_get_httpParam.py
uhf/reader/protocol/app_get_readerInfo.py
uhf/reader/protocol/app_get_readerMac.py
uhf/reader/protocol/app_get_readerTime.py
uhf/reader/protocol/app_get_rs485.py
uhf/reader/protocol/app_get_serialParam.py
uhf/reader/protocol/app_get_tcpMode.py
uhf/reader/protocol/app_get_udpParam.py
uhf/reader/protocol/app_get_whiteList.py
uhf/reader/protocol/app_get_whiteListAction.py
uhf/reader/protocol/app_get_whiteListSwitch.py
uhf/reader/protocol/app_get_wiegand.py
uhf/reader/protocol/app_get_wifiConnectStatus.py
uhf/reader/protocol/app_get_wifiHotspotSearch.py
uhf/reader/protocol/app_get_wifiIp.py
uhf/reader/protocol/app_get_wifiSwitch.py
uhf/reader/protocol/app_gpiOver.py
uhf/reader/protocol/app_gpiStart.py
uhf/reader/protocol/app_heartbeat.py
uhf/reader/protocol/app_import_whiteList.py
uhf/reader/protocol/app_reset.py
uhf/reader/protocol/app_restoreDefault.py
uhf/reader/protocol/app_set_beep.py
uhf/reader/protocol/app_set_beepOnOff.py
uhf/reader/protocol/app_set_breakpointResume.py
uhf/reader/protocol/app_set_easAlarm.py
