Metadata-Version: 2.1
Name: uhfReaderApi-Cykeo
Version: 1.0.3
Summary: ReaderApi
Author: rfid
Platform: linux/Windows
Classifier: Programming Language :: Python :: 3.7
Classifier: Operating System :: OS Independent
License-File: LICENSE
